{
	"id": "b6bd104f-6449-4b3d-b73f-fc1778783cb5",
	"name": "graph-ql-api-postgres web server",
	"values": [
		{
			"key": "host",
			"value": "http://localhost:3001/graphql",
			"type": "default",
			"enabled": true
		},
		{
			"key": "firstName",
			"value": "",
			"type": "any",
			"enabled": true
		},
		{
			"key": "lastName",
			"value": "",
			"type": "any",
			"enabled": true
		},
		{
			"key": "email",
			"value": "",
			"type": "any",
			"enabled": true
		},
		{
			"key": "accessToken",
			"value": "",
			"type": "any",
			"enabled": true
		},
		{
			"key": "refreshToken",
			"value": "",
			"type": "any",
			"enabled": true
		},
		{
			"key": "categoryName",
			"value": "",
			"type": "default",
			"enabled": true
		},
		{
			"key": "categoryDescription",
			"value": "",
			"type": "default",
			"enabled": true
		},
		{
			"key": "categoryParentId",
			"value": "",
			"type": "default",
			"enabled": true
		},
		{
			"key": "categoryId",
			"value": "",
			"type": "default",
			"enabled": true
		},
		{
			"key": "categoryImagePath",
			"value": "",
			"type": "default",
			"enabled": true
		},
		{
			"key": "parentCategoryId",
			"value": "",
			"type": "default",
			"enabled": true
		},
		{
			"key": "productId",
			"value": "",
			"type": "default",
			"enabled": true
		},
		{
			"key": "productName",
			"value": "",
			"type": "default",
			"enabled": true
		},
		{
			"key": "productDescription",
			"value": "",
			"type": "default",
			"enabled": true
		},
		{
			"key": "productPrice",
			"value": "",
			"type": "default",
			"enabled": true
		},
		{
			"key": "productImagePath",
			"value": "",
			"type": "any",
			"enabled": true
		},
		{
			"key": "username",
			"value": "",
			"type": "any",
			"enabled": true
		},
		{
			"key": "password",
			"value": "",
			"type": "any",
			"enabled": true
		},
		{
			"key": "wsHost",
			"value": "lol",
			"type": "default",
			"enabled": true
		}
	],
	"_postman_variable_scope": "environment",
	"_postman_exported_at": "2023-04-05T19:39:29.707Z",
	"_postman_exported_using": "Postman/10.12.4"
}